Metadata-Version: 2.1
Name: ttml
Version: 1.0
Summary: Tensor train based machine learning estimator
Home-page: https://github.com/RikVoorhaar/ttml
Author: Rik Voorhaar
License: UNKNOWN
Keywords: mathematics machine-learning tensors
Platform: UNKNOWN
Classifier: Development Status :: 5 - Production/Stable
Classifier: License :: OSI Approved :: Apache Software License
Classifier: Operating System :: OS Independent
Classifier: Intended Audience :: Science/Research
Classifier: Programming Language :: Python :: 3
Classifier: Topic :: Scientific/Engineering :: Mathematics
Classifier: Topic :: Scientific/Engineering :: Artificial Intelligence
License-File: LICENSE
Requires-Dist: numpy
Requires-Dist: opt-einsum
Requires-Dist: pandas
Requires-Dist: scikit-learn
Requires-Dist: scipy
Requires-Dist: tqdm
Requires-Dist: autoray
Requires-Dist: xgboost
